Metadata-Version: 2.1
Name: DJQ-Distributions
Version: 1.0
Summary: Gaussian and Binomial distributions
Author: Darin Quintana
Author-email: djquintana889@gmail.com
License: UNKNOWN
Platform: UNKNOWN
